{
  "updatedAt": "2026-02-21T10:30:25.848177+00:00",
  "updatedAtAthens": "12:30",
  "matches": [
    {
      "home": "Aston Villa FC",
      "away": "Leeds United FC",
      "homeShort": "Aston Villa",
      "awayShort": "Leeds United",
      "status": "TIMED",
      "minute": null,
      "homeGoals": null,
      "awayGoals": null
    },
    {
      "home": "Brentford FC",
      "away": "Brighton & Hove Albion FC",
      "homeShort": "Brentford",
      "awayShort": "Brighton Hove",
      "status": "TIMED",
      "minute": null,
      "homeGoals": null,
      "awayGoals": null
    },
    {
      "home": "Chelsea FC",
      "away": "Burnley FC",
      "homeShort": "Chelsea",
      "awayShort": "Burnley",
      "status": "TIMED",
      "minute": null,
      "homeGoals": null,
      "awayGoals": null
    },
    {
      "home": "West Ham United FC",
      "away": "AFC Bournemouth",
      "homeShort": "West Ham",
      "awayShort": "Bournemouth",
      "status": "TIMED",
      "minute": null,
      "homeGoals": null,
      "awayGoals": null
    },
    {
      "home": "Manchester City FC",
      "away": "Newcastle United FC",
      "homeShort": "Man City",
      "awayShort": "Newcastle",
      "status": "TIMED",
      "minute": null,
      "homeGoals": null,
      "awayGoals": null
    }
  ]
}